PyChatVerse.py
PyChatVerse-0.0.5.dist-info/LICENSE
PyChatVerse-0.0.5.dist-info/METADATA
PyChatVerse-0.0.5.dist-info/WHEEL
PyChatVerse-0.0.5.dist-info/top_level.txt
PyChatVerse-0.0.5.dist-info/RECORD
