Metadata-Version: 2.1
Name: PyChatVerse
Version: 0.0.5
Summary: PyChatVerse: Real-Time Chat Application for Python
Home-page: https://dayanidigv.github.io/PyChatVerse/
Author: Dayanidi Vadivel
Author-email: <dayanidigv954@gmail.com>
License: MIT
Keywords: python,chat,real-time,communication,messaging,Firebase,PyChatVerse,pychatverse,python chat Application,Real time chat application,Global Chat,Private Chat
Classifier: Development Status :: 3 - Alpha
Classifier: Intended Audience :: Developers
Classifier: Programming Language :: Python :: 3
Classifier: Operating System :: OS Independent
Classifier: License :: OSI Approved :: MIT License
Requires: requests
Requires: pyrebase
License-File: LICENSE
